django_markup/__init__.py
django_markup/defaults.py
django_markup/fields.py
django_markup/filter/__init__.py
django_markup/filter/creole_filter.py
django_markup/filter/linebreaks_filter.py
django_markup/filter/markdown_filter.py
django_markup/filter/none_filter.py
django_markup/filter/rst_filter.py
django_markup/filter/smartypants_filter.py
django_markup/filter/textile_filter.py
django_markup/filter/widont_filter.py
django_markup/markup.py
django_markup/templatetags/__init__.py
django_markup/templatetags/markup_tags.py
django_markup/tests/__init__.py
django_markup/tests/files/rst_header.txt
django_markup/tests/files/rst_header_expected.txt
django_markup/tests/files/rst_raw.txt
django_markup/tests/files/rst_with_pygments.txt
django_markup/tests/files/rst_with_pygments_expected.txt
django_markup/tests/markup_strings.py
django_markup/tests/settings.py
django_markup/tests/templates/test_templatetag.html
django_markup/tests/templates/test_templatetag_filterwrapper.html
django_markup/tests/test_custom_filter.py
django_markup/tests/test_filter.py
django_markup/tests/test_templatetag.py
django_markup-1.9.1.dist-info/LICENSE
django_markup-1.9.1.dist-info/METADATA
django_markup-1.9.1.dist-info/WHEEL
django_markup-1.9.1.dist-info/RECORD
