Metadata-Version: 2.1
Name: django-markup
Version: 1.9.1
Summary: A generic Django application to convert text with specific markup to html.
Home-page: https://github.com/bartTC/django-markup/
License: MIT
Author: Martin Mahner
Author-email: martin@mahner.org
Requires-Python: >=3.8,<4.0
Classifier: Development Status :: 6 - Mature
Classifier: Environment :: Other Environment
Classifier: Environment :: Web Environment
Classifier: Framework :: Django
Classifier: Framework :: Django :: 3.2
Classifier: Framework :: Django :: 4.0
Classifier: Framework :: Django :: 4.1
Classifier: Framework :: Django :: 4.2
Classifier: Framework :: Django :: 5.0
Classifier: Framework :: Django :: 5.1
Classifier: Intended Audience :: Developers
Classifier: License :: OSI Approved :: MIT License
Classifier: Operating System :: OS Independent
Classifier: Programming Language :: Python
Classifier: Programming Language :: Python :: 3
Classifier: Programming Language :: Python :: 3.8
Classifier: Programming Language :: Python :: 3.9
Classifier: Programming Language :: Python :: 3.10
Classifier: Programming Language :: Python :: 3.11
Classifier: Programming Language :: Python :: 3.12
Classifier: Programming Language :: Python :: 3.13
Classifier: Programming Language :: Python :: 3 :: Only
Classifier: Topic :: Internet :: WWW/HTTP
Classifier: Topic :: Software Development :: Libraries :: Python Modules
Requires-Dist: bleach[all-filter-dependencies] (>=3.0)
Requires-Dist: django (>=3.2)
Requires-Dist: docutils[all-filter-dependencies] (>=0.14)
Requires-Dist: markdown[all-filter-dependencies] (>=2.6.9)
Requires-Dist: pygments[all-filter-dependencies] (>=2.10.0)
Requires-Dist: python-creole[all-filter-dependencies] (>=1.3.1)
Requires-Dist: smartypants[all-filter-dependencies] (>=2.0.0)
Requires-Dist: textile[all-filter-dependencies] (>=2.3.16)
